__init__.py
uniqpath.py
uniqpath-0.1.3.dist-info/licenses/LICENSE
uniqpath-0.1.3.dist-info/METADATA
uniqpath-0.1.3.dist-info/WHEEL
uniqpath-0.1.3.dist-info/top_level.txt
uniqpath-0.1.3.dist-info/RECORD
