Metadata-Version: 2.4
Name: uniqpath
Version: 0.1.3
Summary: Generate unique file or directory paths with flexible formatting.
Author-email: Julien Rabault <julienrabault@icloud.com>
License: MIT
Project-URL: Homepage, https://github.com/JulienRabault/uniqpath
Keywords: path,unique,file,directory,utils,suffix
Classifier: Programming Language :: Python :: 3
Classifier: License :: OSI Approved :: MIT License
Classifier: Operating System :: OS Independent
Requires-Python: >=3.8
License-File: LICENSE
Requires-Dist: pytest==8.3.5
Dynamic: license-file
